tree_sitter_printf/__init__.py
tree_sitter_printf/__init__.pyi
tree_sitter_printf/_binding.abi3.so
tree_sitter_printf/binding.c
tree_sitter_printf/py.typed
tree_sitter_printf/queries/highlights.scm
tree_sitter_printf-0.5.0.dist-info/METADATA
tree_sitter_printf-0.5.0.dist-info/WHEEL
tree_sitter_printf-0.5.0.dist-info/top_level.txt
tree_sitter_printf-0.5.0.dist-info/RECORD
tree_sitter_printf-0.5.0.dist-info/licenses/LICENSE
