Metadata-Version: 2.4
Name: tree-sitter-printf
Version: 0.5.0
Summary: printf format grammar for tree-sitter
Author: Peter Stuifzand
Maintainer-email: ObserverOfTime <chronobserver@disroot.org>
License: ISC
Project-URL: Homepage, https://github.com/tree-sitter-grammars/tree-sitter-printf
Keywords: incremental,parsing,tree-sitter,printf
Classifier: Intended Audience :: Developers
Classifier: Topic :: Software Development :: Compilers
Classifier: Topic :: Text Processing :: Linguistic
Classifier: Typing :: Typed
Requires-Python: >=3.10
License-File: LICENSE
Provides-Extra: core
Requires-Dist: tree-sitter~=0.24; extra == "core"
Dynamic: license-file
